pandabear/__init__.py
pandabear/column_checks.py
pandabear/decorators.py
pandabear/exceptions.py
pandabear/model.py
pandabear/model_components.py
pandabear/type_checking.py
pandabear/typehints.py
pandabear-0.9.3.dist-info/METADATA
pandabear-0.9.3.dist-info/WHEEL
pandabear-0.9.3.dist-info/top_level.txt
pandabear-0.9.3.dist-info/RECORD
