Metadata-Version: 2.1
Name: pandabear
Version: 0.9.3
Summary: An runtime vschema validator for Pandas DataFrames.
Home-page: https://github.com/Precis-Digital/pandabear
Author: Ulf Aslak
Author-email: ulf@precisdigital.com
Classifier: Programming Language :: Python
Classifier: Programming Language :: Python :: 3
Classifier: Programming Language :: Python :: 3 :: Only
Classifier: Programming Language :: Python :: 3.8
Classifier: Programming Language :: Python :: 3.9
Classifier: Programming Language :: Python :: 3.10
Classifier: Programming Language :: Python :: 3.11
Requires-Python: >=3.8
Requires-Dist: pandas >=1.5.3
Requires-Dist: numpy >=1.21.0
